stralgo/__init__.py
stralgo/base.py
stralgo/hash/__init__.py
stralgo/hash/sha.py
stralgo-1.1.1.dist-info/LICENSE
stralgo-1.1.1.dist-info/METADATA
stralgo-1.1.1.dist-info/WHEEL
stralgo-1.1.1.dist-info/top_level.txt
stralgo-1.1.1.dist-info/RECORD
